odoo10_addon_delivery_carrier_deposit-10.0.0.2.0-py3.6-nspkg.pth
odoo/addons/delivery_carrier_deposit/README.rst
odoo/addons/delivery_carrier_deposit/__init__.py
odoo/addons/delivery_carrier_deposit/__manifest__.py
odoo/addons/delivery_carrier_deposit/data/ir_sequence_data.xml
odoo/addons/delivery_carrier_deposit/i18n/am.po
odoo/addons/delivery_carrier_deposit/i18n/ar.po
odoo/addons/delivery_carrier_deposit/i18n/bg.po
odoo/addons/delivery_carrier_deposit/i18n/bs.po
odoo/addons/delivery_carrier_deposit/i18n/ca.po
odoo/addons/delivery_carrier_deposit/i18n/ca_ES.po
odoo/addons/delivery_carrier_deposit/i18n/cs.po
odoo/addons/delivery_carrier_deposit/i18n/cs_CZ.po
odoo/addons/delivery_carrier_deposit/i18n/da.po
odoo/addons/delivery_carrier_deposit/i18n/de.po
odoo/addons/delivery_carrier_deposit/i18n/delivery_carrier_deposit.pot
odoo/addons/delivery_carrier_deposit/i18n/el_GR.po
odoo/addons/delivery_carrier_deposit/i18n/en_AU.po
odoo/addons/delivery_carrier_deposit/i18n/en_GB.po
odoo/addons/delivery_carrier_deposit/i18n/es.po
odoo/addons/delivery_carrier_deposit/i18n/es_AR.po
odoo/addons/delivery_carrier_deposit/i18n/es_CL.po
odoo/addons/delivery_carrier_deposit/i18n/es_CO.po
odoo/addons/delivery_carrier_deposit/i18n/es_CR.po
odoo/addons/delivery_carrier_deposit/i18n/es_DO.po
odoo/addons/delivery_carrier_deposit/i18n/es_EC.po
odoo/addons/delivery_carrier_deposit/i18n/es_ES.po
odoo/addons/delivery_carrier_deposit/i18n/es_MX.po
odoo/addons/delivery_carrier_deposit/i18n/es_PE.po
odoo/addons/delivery_carrier_deposit/i18n/es_PY.po
odoo/addons/delivery_carrier_deposit/i18n/es_VE.po
odoo/addons/delivery_carrier_deposit/i18n/et.po
odoo/addons/delivery_carrier_deposit/i18n/eu.po
odoo/addons/delivery_carrier_deposit/i18n/fa.po
odoo/addons/delivery_carrier_deposit/i18n/fi.po
odoo/addons/delivery_carrier_deposit/i18n/fr.po
odoo/addons/delivery_carrier_deposit/i18n/fr_CA.po
odoo/addons/delivery_carrier_deposit/i18n/fr_CH.po
odoo/addons/delivery_carrier_deposit/i18n/fr_FR.po
odoo10_addon_delivery_carrier_deposit-10.0.0.2.0.dist-info/METADATA
odoo10_addon_delivery_carrier_deposit-10.0.0.2.0.dist-info/WHEEL
odoo10_addon_delivery_carrier_deposit-10.0.0.2.0.dist-info/namespace_packages.txt
odoo10_addon_delivery_carrier_deposit-10.0.0.2.0.dist-info/top_level.txt
odoo10_addon_delivery_carrier_deposit-10.0.0.2.0.dist-info/RECORD
