Metadata-Version: 2.1
Name: odoo10-addon-delivery-carrier-deposit
Version: 10.0.0.2.0
Summary: Create deposit slips
Home-page: https://github.com/OCA/delivery-carrier
Author: Akretion,Odoo Community Association (OCA)
Author-email: support@odoo-community.org
License: AGPL-3
Platform: UNKNOWN
Classifier: Programming Language :: Python
Classifier: Framework :: Odoo
Classifier: License :: OSI Approved :: GNU Affero General Public License v3
Requires-Python: ~=2.7
Requires-Dist: odoo10-addon-base-delivery-carrier-label
Requires-Dist: odoo (<10.1dev,>=10.0)
